{"chunk_definitions":[{"row":16,"row_count":1,"visible":true,"expansion_state":0,"options":{"engine":"r","label":"unnamed-chunk-192"},"document_id":"6BC7FE69","chunk_id":"cxe306ujnsefr","chunk_label":"unnamed-chunk-1"},{"row":37,"row_count":1,"visible":true,"expansion_state":0,"options":{"engine":"r","label":"unnamed-chunk-193"},"document_id":"6BC7FE69","chunk_id":"cb4izfpqvn516","chunk_label":"unnamed-chunk-2"},{"row":113,"row_count":1,"visible":true,"expansion_state":0,"options":{"engine":"r","label":"unnamed-chunk-194"},"document_id":"6BC7FE69","chunk_id":"cd3oprcno8eio","chunk_label":"unnamed-chunk-3"},{"row":121,"row_count":1,"visible":true,"expansion_state":0,"options":{"engine":"r","label":"unnamed-chunk-195"},"document_id":"6BC7FE69","chunk_id":"csej6prd74nba","chunk_label":"unnamed-chunk-4"},{"row":130,"row_count":1,"visible":true,"expansion_state":0,"options":{"engine":"r","label":"unnamed-chunk-196"},"document_id":"6BC7FE69","chunk_id":"cw6xik23d8wih","chunk_label":"unnamed-chunk-5"},{"row":134,"row_count":1,"visible":true,"expansion_state":0,"options":{"engine":"r","label":"unnamed-chunk-197"},"document_id":"6BC7FE69","chunk_id":"c8oh12zukutfq","chunk_label":"unnamed-chunk-6"},{"row":142,"row_count":1,"visible":true,"expansion_state":0,"options":{},"document_id":"6BC7FE69","chunk_id":"cgcchz3x5pawc","chunk_label":"unnamed-chunk-7"}],"doc_write_time":1684014094,"chunk_rendered_width":700}